[
  {
    "id": "string",
    "version": "int",
    "title": "string",
    "slug": "string",
    "summary": "string",
    "status": "draft|published|archived|deleted",
    "content": {
      "format": "markdown|html",
      "body": "string"
    },
    "featured_image": {
      "url": "string",
      "alt_text": "string",
      "caption": "string"
    },
    "author": {
      "user_id": "string",
      "name": "string",
      "avatar_url": "string"
    },
    "creation_date": "ISO_8601_datetime",
    "publish_date": "ISO_8601_datetime",
    "last_modified": "ISO_8601_datetime",
    "permissions": {
      "update": "boolean",
      "delete": "boolean"
    },
    "settings": {
      "featured": "boolean",
      "sticky": "boolean"
    }
  },
  {
    "id": "string",
    "version": "int",
    "title": "string",
    "slug": "string",
    "summary": "string",
    "status": "draft|published|archived|deleted",
    "content": {
      "format": "markdown|html",
      "body": "string"
    },
    "featured_image": {
      "url": "string",
      "alt_text": "string",
      "caption": "string"
    },
    "author": {
      "user_id": "string",
      "name": "string",
      "avatar_url": "string"
    },
    "creation_date": "ISO_8601_datetime",
    "publish_date": "ISO_8601_datetime",
    "last_modified": "ISO_8601_datetime",
    "permissions": {
      "update": "boolean",
      "delete": "boolean"
    },
    "settings": {
      "featured": "boolean",
      "sticky": "boolean"
    }
  }
]